qwak_inference/__init__.py
qwak_inference/batch_client/__init__.py
qwak_inference/batch_client/batch_client.py
qwak_inference/batch_client/cloud_provider_client.py
qwak_inference/batch_client/file_serialization.py
qwak_inference/batch_client/instance_validation.py
qwak_inference/batch_client/s3.py
qwak_inference/configuration/__init__.py
qwak_inference/configuration/account.py
qwak_inference/configuration/auth.py
qwak_inference/configuration/log_config.py
qwak_inference/configuration/session.py
qwak_inference/constants.py
qwak_inference/exceptions.py
qwak_inference/feedback_client.py
qwak_inference/realtime_client/__init__.py
qwak_inference/realtime_client/client.py
qwak_inference/realtime_client/rest_helpers.py
qwak_inference-0.2.1.dist-info/LICENSE
qwak_inference-0.2.1.dist-info/METADATA
qwak_inference-0.2.1.dist-info/WHEEL
qwak_inference-0.2.1.dist-info/RECORD
